[
  {
    "value": "1组",
    "label": "1组",
    "children":[
      {
        "label": "1组-任务1",
        "value": {
          "po": {
            "cycle": false,
            "priority": 0,
            "groupId":1,
            "workerId":146,
            "domainId": 129
          },
          "orders": [
            {
              "action": 3,
              "endPointCode": "dj",
              "endPointId": 23060

            }
          ]
        }
      }
    ]
  },
  {
    "value": "2组",
    "label": "2组",
    "children":[
      {
        "label": "2组-任务1",
        "value": {
          "po": {
            "cycle": false,
            "priority": 0,
            "groupId":1,
            "workerId":146,
            "domainId": 129
          },
          "orders": [
            {
              "action": 3,
              "endPointCode": "dj",
              "endPointId": 23060

            }
          ]
        }
      }
    ]
  }
]
